odoo/addons/purchase_tier_validation/README.rst
odoo/addons/purchase_tier_validation/__init__.py
odoo/addons/purchase_tier_validation/__manifest__.py
odoo/addons/purchase_tier_validation/i18n/es.po
odoo/addons/purchase_tier_validation/i18n/purchase_tier_validation.pot
odoo/addons/purchase_tier_validation/i18n/zh_CN.po
odoo/addons/purchase_tier_validation/i18n/zh_TW.po
odoo/addons/purchase_tier_validation/models/__init__.py
odoo/addons/purchase_tier_validation/models/purchase_order.py
odoo/addons/purchase_tier_validation/models/tier_definition.py
odoo/addons/purchase_tier_validation/static/description/icon.png
odoo/addons/purchase_tier_validation/tests/__init__.py
odoo/addons/purchase_tier_validation/tests/common.py
odoo/addons/purchase_tier_validation/tests/test_tier_validation.py
odoo/addons/purchase_tier_validation/tests/tier_validation_tester.py
odoo/addons/purchase_tier_validation/views/purchase_order_view.xml
odoo13_addon_purchase_tier_validation-13.0.1.0.1.dev11.dist-info/METADATA
odoo13_addon_purchase_tier_validation-13.0.1.0.1.dev11.dist-info/WHEEL
odoo13_addon_purchase_tier_validation-13.0.1.0.1.dev11.dist-info/top_level.txt
odoo13_addon_purchase_tier_validation-13.0.1.0.1.dev11.dist-info/RECORD
